trismik/__init__.py
trismik/_async/__init__.py
trismik/_async/_test_transform.py
trismik/_async/client.py
trismik/_async/helpers.py
trismik/_mapper.py
trismik/_sync/__init__.py
trismik/_sync/_test_transform.py
trismik/_sync/client.py
trismik/_sync/helpers.py
trismik/_utils.py
trismik/exceptions.py
trismik/settings.py
trismik/types.py
trismik-1.0.1.dist-info/METADATA
trismik-1.0.1.dist-info/WHEEL
trismik-1.0.1.dist-info/licenses/LICENSE
trismik-1.0.1.dist-info/RECORD
