Metadata-Version: 2.4
Name: trismik
Version: 1.0.1
Summary: 
License-File: LICENSE
Author: Bartosz Kielczewski
Author-email: bk352@cam.ac.uk
Requires-Python: >=3.9, <3.14
Classifier: Programming Language :: Python :: 3
Classifier: Programming Language :: Python :: 3.9
Classifier: Programming Language :: Python :: 3.10
Classifier: Programming Language :: Python :: 3.11
Classifier: Programming Language :: Python :: 3.12
Classifier: Programming Language :: Python :: 3.13
Provides-Extra: examples
Requires-Dist: accelerate (>=1.7.0,<2.0.0) ; extra == "examples"
Requires-Dist: httpx (>=0.27.2,<1.0.0)
Requires-Dist: jupyterlab (>=4.4.8) ; extra == "examples"
Requires-Dist: nest-asyncio (>=1.6.0,<2.0.0)
Requires-Dist: notebook (>=7.4.4,<8.0.0) ; extra == "examples"
Requires-Dist: openai (>=1.81.0,<2.0.0) ; extra == "examples"
Requires-Dist: torch (>=2.8.0,<3.0.0) ; extra == "examples"
Requires-Dist: torchaudio (>=2.7.0,<3.0.0) ; extra == "examples"
Requires-Dist: torchvision (>=0.22.0,<1.0.0) ; extra == "examples"
Requires-Dist: tqdm (>=4.67.1,<5.0.0) ; extra == "examples"
Requires-Dist: transformers (>=4.51.3,<5.0.0) ; extra == "examples"
